SKESPM/SKESPM.py
SKESPM/__init__.py
SKESPM-1.0.2a1.dist-info/LICENSE
SKESPM-1.0.2a1.dist-info/METADATA
SKESPM-1.0.2a1.dist-info/WHEEL
SKESPM-1.0.2a1.dist-info/top_level.txt
SKESPM-1.0.2a1.dist-info/RECORD
