Metadata-Version: 2.1
Name: SKESPM
Version: 1.0.2a1
Summary: This framework help create and manage default project
Home-page: https://github.com/SwiftKRAS-Enterprise-software/project-manager
Author: dssk-esoftware
Author-email: dssk-esoftware@hotmail.com
License: GNU General Public License v3.0
License-File: LICENSE
